setup.py
hzau/__init__.py
hzau/attention.py
hzau/gan.py
hzau/misc.py
hzau.egg-info/PKG-INFO
hzau.egg-info/SOURCES.txt
hzau.egg-info/dependency_links.txt
hzau.egg-info/requires.txt
hzau.egg-info/top_level.txt