Metadata-Version: 2.1
Name: hzau
Version: 0.0.3
Summary: utis
Home-page: https://github/Chang-LeHung
Author: Chang-LeHung
Author-email: chang-lehung@gmail.com
License: UNKNOWN
Platform: UNKNOWN
